LICENSE
MANIFEST.in
README.md
pyproject.toml
imcomp/__init__.py
imcomp/default.cfg
imcomp/fill_table_data.py
imcomp/imcomp.py
imcomp/imcomp_config.py
imcomp/imcomp_table.py
imcomp/imcomp_window.py
imcomp/version.py
imcomp.egg-info/PKG-INFO
imcomp.egg-info/SOURCES.txt
imcomp.egg-info/dependency_links.txt
imcomp.egg-info/entry_points.txt
imcomp.egg-info/requires.txt
imcomp.egg-info/top_level.txt
imcomp/config/default.json
imcomp/help/imcomp_help.html
imcomp/qimtools/__init__.py
imcomp/qimtools/process_image_differences.py